shadowmode/__init__.py
shadowmode/camera_master_parser.py
shadowmode-0.0.2.dist-info/METADATA
shadowmode-0.0.2.dist-info/WHEEL
shadowmode-0.0.2.dist-info/top_level.txt
shadowmode-0.0.2.dist-info/RECORD
