Metadata-Version: 2.1
Name: shadowmode
Version: 0.0.2
Summary: tools for shadowmode
Home-page: UNKNOWN
Author: shadow_mode team
License: UNKNOWN
Platform: UNKNOWN
Requires-Python: >=3.6
